ncrystal_plugin_GraphiticData/__init__.py
ncrystal_plugin_GraphiticData/data/HighNESS_C60_sg202.ncmat
ncrystal_plugin_GraphiticData/data/HighNESS_C8K_sg70.ncmat
ncrystal_plugin_GraphiticData/data/HighNESS_C8Rb_sg70.ncmat
ncrystal_plugin_GraphiticData/data/HighNESS_DeuteratedGraphiteOxideWater_sg1_C8O3D2-D2O.ncmat
ncrystal_plugin_GraphiticData/data/HighNESS_DeuteratedGraphiteOxide_large_model_sg1_C18O3D2.ncmat
ncrystal_plugin_GraphiticData/data/HighNESS_DeuteratedGraphiteOxide_small_model_sg1_C8O3D2.ncmat
ncrystal_plugin_GraphiticData/data/HighNESS_GraphiteOxideWater_sg1_C8O3H2-H2O.ncmat
ncrystal_plugin_GraphiticData/data/HighNESS_GraphiteOxide_large_model_sg1_C18O3H2.ncmat
ncrystal_plugin_GraphiticData/data/HighNESS_GraphiteOxide_small_model_sg1_C8O3H2.ncmat
ncrystal_plugin_graphiticdata-0.0.2.dist-info/LICENSE
ncrystal_plugin_graphiticdata-0.0.2.dist-info/METADATA
ncrystal_plugin_graphiticdata-0.0.2.dist-info/WHEEL
ncrystal_plugin_graphiticdata-0.0.2.dist-info/top_level.txt
ncrystal_plugin_graphiticdata-0.0.2.dist-info/RECORD
