Metadata-Version: 2.2
Name: ncrystal-plugin-GraphiticData
Version: 0.0.2
Summary: NCMAT data files for graphite oxides and fullerite (C60).
License: 
Project-URL: Homepage, https://github.com/highness-eu/ncmat-graphitic
Project-URL: Bug Tracker, https://github.com/mctools/ncrystal/issues
Classifier: Programming Language :: Python :: 3
Classifier: License :: OSI Approved :: Apache Software License
License-File: LICENSE
Requires-Dist: ncrystal-pypluginmgr>=0.0.5
